[
    {
        "path": ".github/workflows/deploy.yml",
        "filename": "deploy.yml",
        "parent_directory": ".github\\workflows",
        "extension": ".yml",
        "language": "Unknown",
        "category": "Configuration",
        "directory_depth": 2,
        "size": 2126,
        "sha": "579ea465e5ecea4f6c09d65b471505d477c064e9",
        "git_url": "https://api.github.com/repos/rmunate/SpellNumber/git/blobs/579ea465e5ecea4f6c09d65b471505d477c064e9",
        "is_test_file": false,
        "is_documentation": false,
        "is_config_file": false,
        "is_hidden": false,
        "is_binary": false
    },
    {
        "path": ".gitignore",
        "filename": ".gitignore",
        "parent_directory": ".",
        "extension": "",
        "language": "Unknown",
        "category": "Other",
        "directory_depth": 0,
        "size": 359,
        "sha": "1ebee78dca7598e4f453275dcb6e05e8d5928acd",
        "git_url": "https://api.github.com/repos/rmunate/SpellNumber/git/blobs/1ebee78dca7598e4f453275dcb6e05e8d5928acd",
        "is_test_file": false,
        "is_documentation": false,
        "is_config_file": true,
        "is_hidden": true,
        "is_binary": false
    },
    {
        "path": "LICENSE.md",
        "filename": "LICENSE.md",
        "parent_directory": ".",
        "extension": ".md",
        "language": "Unknown",
        "category": "Documentation",
        "directory_depth": 0,
        "size": 1084,
        "sha": "4112025e536578b1d7faceb05fba97b6ab379b86",
        "git_url": "https://api.github.com/repos/rmunate/SpellNumber/git/blobs/4112025e536578b1d7faceb05fba97b6ab379b86",
        "is_test_file": false,
        "is_documentation": false,
        "is_config_file": false,
        "is_hidden": false,
        "is_binary": false
    },
    {
        "path": "README.md",
        "filename": "README.md",
        "parent_directory": ".",
        "extension": ".md",
        "language": "Unknown",
        "category": "Documentation",
        "directory_depth": 0,
        "size": 3456,
        "sha": "d5b0a23588bc5dc8d186e4071a84cf85219273d6",
        "git_url": "https://api.github.com/repos/rmunate/SpellNumber/git/blobs/d5b0a23588bc5dc8d186e4071a84cf85219273d6",
        "is_test_file": false,
        "is_documentation": true,
        "is_config_file": false,
        "is_hidden": false,
        "is_binary": false
    },
    {
        "path": "composer.json",
        "filename": "composer.json",
        "parent_directory": ".",
        "extension": ".json",
        "language": "Unknown",
        "category": "Configuration",
        "directory_depth": 0,
        "size": 2540,
        "sha": "261da28948116f51d24a785b23363859977b8a8c",
        "git_url": "https://api.github.com/repos/rmunate/SpellNumber/git/blobs/261da28948116f51d24a785b23363859977b8a8c",
        "is_test_file": false,
        "is_documentation": false,
        "is_config_file": false,
        "is_hidden": false,
        "is_binary": false
    },
    {
        "path": "config/spell-number.php",
        "filename": "spell-number.php",
        "parent_directory": "config",
        "extension": ".php",
        "language": "PHP",
        "category": "Source Code",
        "directory_depth": 1,
        "size": 3948,
        "sha": "589ba7126088a689188a340e4c2931f8b6355c81",
        "git_url": "https://api.github.com/repos/rmunate/SpellNumber/git/blobs/589ba7126088a689188a340e4c2931f8b6355c81",
        "is_test_file": false,
        "is_documentation": false,
        "is_config_file": false,
        "is_hidden": false,
        "is_binary": false
    },
    {
        "path": "docs/.vitepress/config.mts",
        "filename": "config.mts",
        "parent_directory": "docs\\.vitepress",
        "extension": ".mts",
        "language": "Unknown",
        "category": "Documentation",
        "directory_depth": 2,
        "size": 3697,
        "sha": "c3d2e0ff481dda278a7a00f9c2b12523d80f8a72",
        "git_url": "https://api.github.com/repos/rmunate/SpellNumber/git/blobs/c3d2e0ff481dda278a7a00f9c2b12523d80f8a72",
        "is_test_file": false,
        "is_documentation": true,
        "is_config_file": false,
        "is_hidden": false,
        "is_binary": false
    },
    {
        "path": "docs/contribute/contribution.md",
        "filename": "contribution.md",
        "parent_directory": "docs\\contribute",
        "extension": ".md",
        "language": "Unknown",
        "category": "Documentation",
        "directory_depth": 2,
        "size": 3549,
        "sha": "b98ab95ccef15d2bd56d7d8734972dab621c0e6e",
        "git_url": "https://api.github.com/repos/rmunate/SpellNumber/git/blobs/b98ab95ccef15d2bd56d7d8734972dab621c0e6e",
        "is_test_file": false,
        "is_documentation": true,
        "is_config_file": false,
        "is_hidden": false,
        "is_binary": false
    },
    {
        "path": "docs/contribute/report-bugs.md",
        "filename": "report-bugs.md",
        "parent_directory": "docs\\contribute",
        "extension": ".md",
        "language": "Unknown",
        "category": "Documentation",
        "directory_depth": 2,
        "size": 393,
        "sha": "eb9bd2efdd09ccaa3bfe554f1b08653c94ae18a8",
        "git_url": "https://api.github.com/repos/rmunate/SpellNumber/git/blobs/eb9bd2efdd09ccaa3bfe554f1b08653c94ae18a8",
        "is_test_file": false,
        "is_documentation": true,
        "is_config_file": false,
        "is_hidden": false,
        "is_binary": false
    },
    {
        "path": "docs/getting-started/changelog.md",
        "filename": "changelog.md",
        "parent_directory": "docs\\getting-started",
        "extension": ".md",
        "language": "Unknown",
        "category": "Documentation",
        "directory_depth": 2,
        "size": 1041,
        "sha": "2aaa703789d815d3af777c99f3a378ff07bf1293",
        "git_url": "https://api.github.com/repos/rmunate/SpellNumber/git/blobs/2aaa703789d815d3af777c99f3a378ff07bf1293",
        "is_test_file": false,
        "is_documentation": true,
        "is_config_file": false,
        "is_hidden": false,
        "is_binary": false
    },
    {
        "path": "docs/getting-started/installation.md",
        "filename": "installation.md",
        "parent_directory": "docs\\getting-started",
        "extension": ".md",
        "language": "Unknown",
        "category": "Documentation",
        "directory_depth": 2,
        "size": 595,
        "sha": "cfcf93a8cd6c97e8f1be7296470a5add3f3f2336",
        "git_url": "https://api.github.com/repos/rmunate/SpellNumber/git/blobs/cfcf93a8cd6c97e8f1be7296470a5add3f3f2336",
        "is_test_file": false,
        "is_documentation": true,
        "is_config_file": false,
        "is_hidden": false,
        "is_binary": false
    },
    {
        "path": "docs/getting-started/introduction.md",
        "filename": "introduction.md",
        "parent_directory": "docs\\getting-started",
        "extension": ".md",
        "language": "Unknown",
        "category": "Documentation",
        "directory_depth": 2,
        "size": 629,
        "sha": "a1e84a18a12527de7c158e3ab5ffd48703da4af7",
        "git_url": "https://api.github.com/repos/rmunate/SpellNumber/git/blobs/a1e84a18a12527de7c158e3ab5ffd48703da4af7",
        "is_test_file": false,
        "is_documentation": true,
        "is_config_file": false,
        "is_hidden": false,
        "is_binary": false
    },
    {
        "path": "docs/getting-started/publish-vendor.md",
        "filename": "publish-vendor.md",
        "parent_directory": "docs\\getting-started",
        "extension": ".md",
        "language": "Unknown",
        "category": "Documentation",
        "directory_depth": 2,
        "size": 720,
        "sha": "76908d6a08fa327e52c5830c02e12315a3279d2b",
        "git_url": "https://api.github.com/repos/rmunate/SpellNumber/git/blobs/76908d6a08fa327e52c5830c02e12315a3279d2b",
        "is_test_file": false,
        "is_documentation": true,
        "is_config_file": false,
        "is_hidden": false,
        "is_binary": false
    },
    {
        "path": "docs/index.md",
        "filename": "index.md",
        "parent_directory": "docs",
        "extension": ".md",
        "language": "Unknown",
        "category": "Documentation",
        "directory_depth": 1,
        "size": 1057,
        "sha": "06a57996859ebd153dc8d8961f1e13b8fd622806",
        "git_url": "https://api.github.com/repos/rmunate/SpellNumber/git/blobs/06a57996859ebd153dc8d8961f1e13b8fd622806",
        "is_test_file": false,
        "is_documentation": true,
        "is_config_file": false,
        "is_hidden": false,
        "is_binary": false
    },
    {
        "path": "docs/public/css/style.css",
        "filename": "style.css",
        "parent_directory": "docs\\public\\css",
        "extension": ".css",
        "language": "CSS",
        "category": "Documentation",
        "directory_depth": 3,
        "size": 238,
        "sha": "de8be43b75315691e3881edd6667bb9382c7fe89",
        "git_url": "https://api.github.com/repos/rmunate/SpellNumber/git/blobs/de8be43b75315691e3881edd6667bb9382c7fe89",
        "is_test_file": false,
        "is_documentation": true,
        "is_config_file": false,
        "is_hidden": false,
        "is_binary": false
    },
    {
        "path": "docs/public/img/favicon.svg",
        "filename": "favicon.svg",
        "parent_directory": "docs\\public\\img",
        "extension": ".svg",
        "language": "Unknown",
        "category": "Binary",
        "directory_depth": 3,
        "size": 1219164,
        "sha": "a589e2924d6f9ee3d39420e7e8ed5a3c4f089ec1",
        "git_url": "https://api.github.com/repos/rmunate/SpellNumber/git/blobs/a589e2924d6f9ee3d39420e7e8ed5a3c4f089ec1",
        "is_test_file": false,
        "is_documentation": true,
        "is_config_file": false,
        "is_hidden": false,
        "is_binary": true
    },
    {
        "path": "docs/public/img/laravel-red.svg",
        "filename": "laravel-red.svg",
        "parent_directory": "docs\\public\\img",
        "extension": ".svg",
        "language": "Unknown",
        "category": "Binary",
        "directory_depth": 3,
        "size": 4661,
        "sha": "40e9f20e84232140c5138f1e8dfd57eee8643c06",
        "git_url": "https://api.github.com/repos/rmunate/SpellNumber/git/blobs/40e9f20e84232140c5138f1e8dfd57eee8643c06",
        "is_test_file": false,
        "is_documentation": true,
        "is_config_file": false,
        "is_hidden": false,
        "is_binary": true
    },
    {
        "path": "docs/public/img/laravel_black.svg",
        "filename": "laravel_black.svg",
        "parent_directory": "docs\\public\\img",
        "extension": ".svg",
        "language": "Unknown",
        "category": "Binary",
        "directory_depth": 3,
        "size": 2303,
        "sha": "9e91da33d854d563f42820f01171646f2d0f5f67",
        "git_url": "https://api.github.com/repos/rmunate/SpellNumber/git/blobs/9e91da33d854d563f42820f01171646f2d0f5f67",
        "is_test_file": false,
        "is_documentation": true,
        "is_config_file": false,
        "is_hidden": false,
        "is_binary": true
    },
    {
        "path": "docs/public/img/logo-full-scream.png",
        "filename": "logo-full-scream.png",
        "parent_directory": "docs\\public\\img",
        "extension": ".png",
        "language": "Unknown",
        "category": "Binary",
        "directory_depth": 3,
        "size": 1154200,
        "sha": "4a0d4128f15f986ee4ad1db2c02c519d33301a48",
        "git_url": "https://api.github.com/repos/rmunate/SpellNumber/git/blobs/4a0d4128f15f986ee4ad1db2c02c519d33301a48",
        "is_test_file": false,
        "is_documentation": true,
        "is_config_file": false,
        "is_hidden": false,
        "is_binary": true
    },
    {
        "path": "docs/public/img/logo-github.png",
        "filename": "logo-github.png",
        "parent_directory": "docs\\public\\img",
        "extension": ".png",
        "language": "Unknown",
        "category": "Binary",
        "directory_depth": 3,
        "size": 1247546,
        "sha": "7fef249d1fee09094dd9d9f89665c3d651c67a3e",
        "git_url": "https://api.github.com/repos/rmunate/SpellNumber/git/blobs/7fef249d1fee09094dd9d9f89665c3d651c67a3e",
        "is_test_file": false,
        "is_documentation": true,
        "is_config_file": false,
        "is_hidden": false,
        "is_binary": true
    },
    {
        "path": "docs/public/img/logo.png",
        "filename": "logo.png",
        "parent_directory": "docs\\public\\img",
        "extension": ".png",
        "language": "Unknown",
        "category": "Binary",
        "directory_depth": 3,
        "size": 927952,
        "sha": "dff21ab6f32272c98389b3aacbdaae6a9834e03a",
        "git_url": "https://api.github.com/repos/rmunate/SpellNumber/git/blobs/dff21ab6f32272c98389b3aacbdaae6a9834e03a",
        "is_test_file": false,
        "is_documentation": true,
        "is_config_file": false,
        "is_hidden": false,
        "is_binary": true
    },
    {
        "path": "docs/usage/config-custom-callback.md",
        "filename": "config-custom-callback.md",
        "parent_directory": "docs\\usage",
        "extension": ".md",
        "language": "Unknown",
        "category": "Documentation",
        "directory_depth": 2,
        "size": 1355,
        "sha": "d10b45b77be5834e27cc3bbe6dfdb1ff6a01a991",
        "git_url": "https://api.github.com/repos/rmunate/SpellNumber/git/blobs/d10b45b77be5834e27cc3bbe6dfdb1ff6a01a991",
        "is_test_file": false,
        "is_documentation": true,
        "is_config_file": false,
        "is_hidden": false,
        "is_binary": false
    },
    {
        "path": "docs/usage/config-file.md",
        "filename": "config-file.md",
        "parent_directory": "docs\\usage",
        "extension": ".md",
        "language": "Unknown",
        "category": "Documentation",
        "directory_depth": 2,
        "size": 3705,
        "sha": "0402944464b344c0cef4515252e2b1ef518eda7e",
        "git_url": "https://api.github.com/repos/rmunate/SpellNumber/git/blobs/0402944464b344c0cef4515252e2b1ef518eda7e",
        "is_test_file": false,
        "is_documentation": true,
        "is_config_file": false,
        "is_hidden": false,
        "is_binary": false
    },
    {
        "path": "docs/usage/languages-available.md",
        "filename": "languages-available.md",
        "parent_directory": "docs\\usage",
        "extension": ".md",
        "language": "Unknown",
        "category": "Documentation",
        "directory_depth": 2,
        "size": 2150,
        "sha": "f0b01a9bd9b7d48a43a4c388ca905c7a4262d6e4",
        "git_url": "https://api.github.com/repos/rmunate/SpellNumber/git/blobs/f0b01a9bd9b7d48a43a4c388ca905c7a4262d6e4",
        "is_test_file": false,
        "is_documentation": true,
        "is_config_file": false,
        "is_hidden": false,
        "is_binary": false
    },
    {
        "path": "docs/usage/macroable.md",
        "filename": "macroable.md",
        "parent_directory": "docs\\usage",
        "extension": ".md",
        "language": "Unknown",
        "category": "Documentation",
        "directory_depth": 2,
        "size": 2316,
        "sha": "5956f0819b72972be377008d60ee3bb3625da015",
        "git_url": "https://api.github.com/repos/rmunate/SpellNumber/git/blobs/5956f0819b72972be377008d60ee3bb3625da015",
        "is_test_file": false,
        "is_documentation": true,
        "is_config_file": false,
        "is_hidden": false,
        "is_binary": false
    },
    {
        "path": "docs/usage/numbers-to-letters.md",
        "filename": "numbers-to-letters.md",
        "parent_directory": "docs\\usage",
        "extension": ".md",
        "language": "Unknown",
        "category": "Documentation",
        "directory_depth": 2,
        "size": 2911,
        "sha": "23a8041a3a0ca1f613d53dd4e95875254812e461",
        "git_url": "https://api.github.com/repos/rmunate/SpellNumber/git/blobs/23a8041a3a0ca1f613d53dd4e95875254812e461",
        "is_test_file": false,
        "is_documentation": true,
        "is_config_file": false,
        "is_hidden": false,
        "is_binary": false
    },
    {
        "path": "docs/usage/numbers-to-money.md",
        "filename": "numbers-to-money.md",
        "parent_directory": "docs\\usage",
        "extension": ".md",
        "language": "Unknown",
        "category": "Documentation",
        "directory_depth": 2,
        "size": 3298,
        "sha": "8a3275b8168fecac83e25948c15d6a0901fcd33c",
        "git_url": "https://api.github.com/repos/rmunate/SpellNumber/git/blobs/8a3275b8168fecac83e25948c15d6a0901fcd33c",
        "is_test_file": false,
        "is_documentation": true,
        "is_config_file": false,
        "is_hidden": false,
        "is_binary": false
    },
    {
        "path": "docs/usage/numbers-to-ordinal.md",
        "filename": "numbers-to-ordinal.md",
        "parent_directory": "docs\\usage",
        "extension": ".md",
        "language": "Unknown",
        "category": "Documentation",
        "directory_depth": 2,
        "size": 1939,
        "sha": "3d27af04b67eac499c67e39bc0ff0eea91397359",
        "git_url": "https://api.github.com/repos/rmunate/SpellNumber/git/blobs/3d27af04b67eac499c67e39bc0ff0eea91397359",
        "is_test_file": false,
        "is_documentation": true,
        "is_config_file": false,
        "is_hidden": false,
        "is_binary": false
    },
    {
        "path": "package-lock.json",
        "filename": "package-lock.json",
        "parent_directory": ".",
        "extension": ".json",
        "language": "Unknown",
        "category": "Configuration",
        "directory_depth": 0,
        "size": 44944,
        "sha": "92e31a8424c556246b52d9445f694481178476a3",
        "git_url": "https://api.github.com/repos/rmunate/SpellNumber/git/blobs/92e31a8424c556246b52d9445f694481178476a3",
        "is_test_file": false,
        "is_documentation": false,
        "is_config_file": true,
        "is_hidden": false,
        "is_binary": false
    },
    {
        "path": "package.json",
        "filename": "package.json",
        "parent_directory": ".",
        "extension": ".json",
        "language": "Unknown",
        "category": "Configuration",
        "directory_depth": 0,
        "size": 208,
        "sha": "5450f5e193ae70ee63ffa8e497f42a1952baa8c1",
        "git_url": "https://api.github.com/repos/rmunate/SpellNumber/git/blobs/5450f5e193ae70ee63ffa8e497f42a1952baa8c1",
        "is_test_file": false,
        "is_documentation": false,
        "is_config_file": true,
        "is_hidden": false,
        "is_binary": false
    },
    {
        "path": "src/Bases/BaseSpellNumber.php",
        "filename": "BaseSpellNumber.php",
        "parent_directory": "src\\Bases",
        "extension": ".php",
        "language": "PHP",
        "category": "Source Code",
        "directory_depth": 2,
        "size": 3458,
        "sha": "044380e0627fb4c82ecd8088624efe48f417be44",
        "git_url": "https://api.github.com/repos/rmunate/SpellNumber/git/blobs/044380e0627fb4c82ecd8088624efe48f417be44",
        "is_test_file": false,
        "is_documentation": false,
        "is_config_file": false,
        "is_hidden": false,
        "is_binary": false
    },
    {
        "path": "src/Bases/BaseSpellNumberValidator.php",
        "filename": "BaseSpellNumberValidator.php",
        "parent_directory": "src\\Bases",
        "extension": ".php",
        "language": "PHP",
        "category": "Source Code",
        "directory_depth": 2,
        "size": 594,
        "sha": "e085bb46e4920b5d12d949fdfe072836be6ed096",
        "git_url": "https://api.github.com/repos/rmunate/SpellNumber/git/blobs/e085bb46e4920b5d12d949fdfe072836be6ed096",
        "is_test_file": false,
        "is_documentation": false,
        "is_config_file": false,
        "is_hidden": false,
        "is_binary": false
    },
    {
        "path": "src/Callback/DataResponse.php",
        "filename": "DataResponse.php",
        "parent_directory": "src\\Callback",
        "extension": ".php",
        "language": "PHP",
        "category": "Source Code",
        "directory_depth": 2,
        "size": 2429,
        "sha": "34f39eacafa2cf8b472b61da3a4af1490c8f233a",
        "git_url": "https://api.github.com/repos/rmunate/SpellNumber/git/blobs/34f39eacafa2cf8b472b61da3a4af1490c8f233a",
        "is_test_file": false,
        "is_documentation": false,
        "is_config_file": false,
        "is_hidden": false,
        "is_binary": false
    },
    {
        "path": "src/Exceptions/SpellNumberExceptions.php",
        "filename": "SpellNumberExceptions.php",
        "parent_directory": "src\\Exceptions",
        "extension": ".php",
        "language": "PHP",
        "category": "Source Code",
        "directory_depth": 2,
        "size": 895,
        "sha": "7b89ea51bef948510545d8802ca4f9a5fe0a792a",
        "git_url": "https://api.github.com/repos/rmunate/SpellNumber/git/blobs/7b89ea51bef948510545d8802ca4f9a5fe0a792a",
        "is_test_file": false,
        "is_documentation": false,
        "is_config_file": false,
        "is_hidden": false,
        "is_binary": false
    },
    {
        "path": "src/Langs/Langs.php",
        "filename": "Langs.php",
        "parent_directory": "src\\Langs",
        "extension": ".php",
        "language": "PHP",
        "category": "Source Code",
        "directory_depth": 2,
        "size": 2413,
        "sha": "14300355a95ab968a2ff90ab81aa91701eafee49",
        "git_url": "https://api.github.com/repos/rmunate/SpellNumber/git/blobs/14300355a95ab968a2ff90ab81aa91701eafee49",
        "is_test_file": false,
        "is_documentation": false,
        "is_config_file": false,
        "is_hidden": false,
        "is_binary": false
    },
    {
        "path": "src/Langs/Replaces.php",
        "filename": "Replaces.php",
        "parent_directory": "src\\Langs",
        "extension": ".php",
        "language": "PHP",
        "category": "Source Code",
        "directory_depth": 2,
        "size": 4307,
        "sha": "22cdf9d431079cf31e329180ec224119f8de1496",
        "git_url": "https://api.github.com/repos/rmunate/SpellNumber/git/blobs/22cdf9d431079cf31e329180ec224119f8de1496",
        "is_test_file": false,
        "is_documentation": false,
        "is_config_file": false,
        "is_hidden": false,
        "is_binary": false
    },
    {
        "path": "src/Miscellaneous/Utilities.php",
        "filename": "Utilities.php",
        "parent_directory": "src\\Miscellaneous",
        "extension": ".php",
        "language": "PHP",
        "category": "Source Code",
        "directory_depth": 2,
        "size": 7158,
        "sha": "38d3de8ad671d7db21d5df9dabb1ab4f6dcedc29",
        "git_url": "https://api.github.com/repos/rmunate/SpellNumber/git/blobs/38d3de8ad671d7db21d5df9dabb1ab4f6dcedc29",
        "is_test_file": false,
        "is_documentation": false,
        "is_config_file": false,
        "is_hidden": false,
        "is_binary": false
    },
    {
        "path": "src/Miscellaneous/Words.php",
        "filename": "Words.php",
        "parent_directory": "src\\Miscellaneous",
        "extension": ".php",
        "language": "PHP",
        "category": "Source Code",
        "directory_depth": 2,
        "size": 2053,
        "sha": "b91810eba81750065d68262c627330e88643d7cd",
        "git_url": "https://api.github.com/repos/rmunate/SpellNumber/git/blobs/b91810eba81750065d68262c627330e88643d7cd",
        "is_test_file": false,
        "is_documentation": false,
        "is_config_file": false,
        "is_hidden": false,
        "is_binary": false
    },
    {
        "path": "src/Providers/SpellNumberProvider.php",
        "filename": "SpellNumberProvider.php",
        "parent_directory": "src\\Providers",
        "extension": ".php",
        "language": "PHP",
        "category": "Source Code",
        "directory_depth": 2,
        "size": 608,
        "sha": "b6eabd25d1c0053ffc16c324b3e9dc167c4ea17d",
        "git_url": "https://api.github.com/repos/rmunate/SpellNumber/git/blobs/b6eabd25d1c0053ffc16c324b3e9dc167c4ea17d",
        "is_test_file": false,
        "is_documentation": false,
        "is_config_file": false,
        "is_hidden": false,
        "is_binary": false
    },
    {
        "path": "src/SpellNumber.php",
        "filename": "SpellNumber.php",
        "parent_directory": "src",
        "extension": ".php",
        "language": "PHP",
        "category": "Source Code",
        "directory_depth": 1,
        "size": 10619,
        "sha": "c230846d935ec6d307405363727f5ef5031f1c73",
        "git_url": "https://api.github.com/repos/rmunate/SpellNumber/git/blobs/c230846d935ec6d307405363727f5ef5031f1c73",
        "is_test_file": false,
        "is_documentation": false,
        "is_config_file": false,
        "is_hidden": false,
        "is_binary": false
    },
    {
        "path": "src/Traits/Accesor.php",
        "filename": "Accesor.php",
        "parent_directory": "src\\Traits",
        "extension": ".php",
        "language": "PHP",
        "category": "Source Code",
        "directory_depth": 2,
        "size": 545,
        "sha": "135e0dad6f9b85574c6886815264f03f1c2962c3",
        "git_url": "https://api.github.com/repos/rmunate/SpellNumber/git/blobs/135e0dad6f9b85574c6886815264f03f1c2962c3",
        "is_test_file": false,
        "is_documentation": false,
        "is_config_file": false,
        "is_hidden": false,
        "is_binary": false
    },
    {
        "path": "src/Traits/Locale.php",
        "filename": "Locale.php",
        "parent_directory": "src\\Traits",
        "extension": ".php",
        "language": "PHP",
        "category": "Source Code",
        "directory_depth": 2,
        "size": 771,
        "sha": "2e005cd5cf60b22908b2783e10cdb1b9716b5a90",
        "git_url": "https://api.github.com/repos/rmunate/SpellNumber/git/blobs/2e005cd5cf60b22908b2783e10cdb1b9716b5a90",
        "is_test_file": false,
        "is_documentation": false,
        "is_config_file": false,
        "is_hidden": false,
        "is_binary": false
    },
    {
        "path": "src/Validator/SpellNumberValidator.php",
        "filename": "SpellNumberValidator.php",
        "parent_directory": "src\\Validator",
        "extension": ".php",
        "language": "PHP",
        "category": "Source Code",
        "directory_depth": 2,
        "size": 2235,
        "sha": "1f9c986e40c80b64cdf75a49ec8f7eb56b545384",
        "git_url": "https://api.github.com/repos/rmunate/SpellNumber/git/blobs/1f9c986e40c80b64cdf75a49ec8f7eb56b545384",
        "is_test_file": false,
        "is_documentation": false,
        "is_config_file": false,
        "is_hidden": false,
        "is_binary": false
    },
    {
        "path": "src/Validator/Traits/CommonValidate.php",
        "filename": "CommonValidate.php",
        "parent_directory": "src\\Validator\\Traits",
        "extension": ".php",
        "language": "PHP",
        "category": "Source Code",
        "directory_depth": 3,
        "size": 3285,
        "sha": "af73a98877729992d484e553a7d7d1984e0216be",
        "git_url": "https://api.github.com/repos/rmunate/SpellNumber/git/blobs/af73a98877729992d484e553a7d7d1984e0216be",
        "is_test_file": false,
        "is_documentation": false,
        "is_config_file": false,
        "is_hidden": false,
        "is_binary": false
    },
    {
        "path": "src/Wrappers/NumberFormatterWrapper.php",
        "filename": "NumberFormatterWrapper.php",
        "parent_directory": "src\\Wrappers",
        "extension": ".php",
        "language": "PHP",
        "category": "Source Code",
        "directory_depth": 2,
        "size": 1240,
        "sha": "90a8f8707b5555366e9c4a8a89a3d80d27f57a87",
        "git_url": "https://api.github.com/repos/rmunate/SpellNumber/git/blobs/90a8f8707b5555366e9c4a8a89a3d80d27f57a87",
        "is_test_file": false,
        "is_documentation": false,
        "is_config_file": false,
        "is_hidden": false,
        "is_binary": false
    },
    {
        "path": "test/SpellNumberTest.php",
        "filename": "SpellNumberTest.php",
        "parent_directory": "test",
        "extension": ".php",
        "language": "PHP",
        "category": "Test",
        "directory_depth": 1,
        "size": 2564,
        "sha": "b569501a6eb972e9f659ea11224444b6d726fa4e",
        "git_url": "https://api.github.com/repos/rmunate/SpellNumber/git/blobs/b569501a6eb972e9f659ea11224444b6d726fa4e",
        "is_test_file": true,
        "is_documentation": false,
        "is_config_file": false,
        "is_hidden": false,
        "is_binary": false
    }
]