[
    {
        "id": 3404312395,
        "number": 242,
        "title": "Bump AutoMapper and Microsoft.Extensions.Options",
        "state": "closed",
        "draft": false,
        "merged": false,
        "created_at": "2026-03-16T12:51:02Z",
        "updated_at": "2026-03-19T13:50:04Z",
        "closed_at": "2026-03-19T13:49:53Z",
        "merged_at": null,
        "author": "dependabot[bot]",
        "base_branch": "master",
        "head_branch": "dependabot/nuget/src/Common/BankSystem.Common/multi-4abdd3b4f3",
        "commits": null,
        "changed_files": null,
        "additions": null,
        "deletions": null,
        "comments": null,
        "review_comments": null,
        "labels": [
            "dependencies",
            ".NET"
        ],
        "url": "https://github.com/banksystembg/BankSystem/pull/242"
    },
    {
        "id": 3397760483,
        "number": 241,
        "title": "Bump AutoMapper and Microsoft.Extensions.Options",
        "state": "closed",
        "draft": false,
        "merged": false,
        "created_at": "2026-03-14T01:13:42Z",
        "updated_at": "2026-03-16T12:51:08Z",
        "closed_at": "2026-03-16T12:51:05Z",
        "merged_at": null,
        "author": "dependabot[bot]",
        "base_branch": "master",
        "head_branch": "dependabot/nuget/src/Common/BankSystem.Common/multi-ee8e396dfa",
        "commits": null,
        "changed_files": null,
        "additions": null,
        "deletions": null,
        "comments": null,
        "review_comments": null,
        "labels": [
            "dependencies",
            ".NET"
        ],
        "url": "https://github.com/banksystembg/BankSystem/pull/241"
    },
    {
        "id": 1911871864,
        "number": 236,
        "title": "Update CardServiceTests.cs",
        "state": "closed",
        "draft": false,
        "merged": false,
        "created_at": "2024-06-10T10:18:45Z",
        "updated_at": "2024-06-10T10:19:48Z",
        "closed_at": "2024-06-10T10:19:48Z",
        "merged_at": null,
        "author": "Meet5801",
        "base_branch": "master",
        "head_branch": "patch-1",
        "commits": null,
        "changed_files": null,
        "additions": null,
        "deletions": null,
        "comments": null,
        "review_comments": null,
        "labels": [],
        "url": "https://github.com/banksystembg/BankSystem/pull/236"
    },
    {
        "id": 1196170656,
        "number": 231,
        "title": "Create FUNDING.yml",
        "state": "closed",
        "draft": false,
        "merged": false,
        "created_at": "2023-01-13T04:09:04Z",
        "updated_at": "2023-01-16T15:48:34Z",
        "closed_at": "2023-01-16T15:48:34Z",
        "merged_at": null,
        "author": "cryptostylegq",
        "base_branch": "master",
        "head_branch": "master",
        "commits": null,
        "changed_files": null,
        "additions": null,
        "deletions": null,
        "comments": null,
        "review_comments": null,
        "labels": [],
        "url": "https://github.com/banksystembg/BankSystem/pull/231"
    },
    {
        "id": 584205529,
        "number": 228,
        "title": "Rename dotnet.yml to main.yml",
        "state": "closed",
        "draft": false,
        "merged": true,
        "created_at": "2021-03-03T19:20:54Z",
        "updated_at": "2021-03-03T19:36:06Z",
        "closed_at": "2021-03-03T19:36:06Z",
        "merged_at": "2021-03-03T19:36:05Z",
        "author": "melikpehlivanov",
        "base_branch": "master",
        "head_branch": "rename-github-workflow-file",
        "commits": null,
        "changed_files": null,
        "additions": null,
        "deletions": null,
        "comments": null,
        "review_comments": null,
        "labels": [],
        "url": "https://github.com/banksystembg/BankSystem/pull/228"
    },
    {
        "id": 584188864,
        "number": 227,
        "title": "Patch github actions workflow",
        "state": "closed",
        "draft": false,
        "merged": true,
        "created_at": "2021-03-03T18:52:08Z",
        "updated_at": "2021-03-03T19:08:24Z",
        "closed_at": "2021-03-03T18:52:21Z",
        "merged_at": "2021-03-03T18:52:21Z",
        "author": "melikpehlivanov",
        "base_branch": "master",
        "head_branch": "patch-github-actions",
        "commits": null,
        "changed_files": null,
        "additions": null,
        "deletions": null,
        "comments": null,
        "review_comments": null,
        "labels": [],
        "url": "https://github.com/banksystembg/BankSystem/pull/227"
    },
    {
        "id": 584113877,
        "number": 226,
        "title": "Update dotnet.yml",
        "state": "closed",
        "draft": false,
        "merged": false,
        "created_at": "2021-03-03T16:56:32Z",
        "updated_at": "2021-03-03T17:00:14Z",
        "closed_at": "2021-03-03T16:59:42Z",
        "merged_at": null,
        "author": "melikpehlivanov",
        "base_branch": "master",
        "head_branch": "melikpehlivanov-patch-1",
        "commits": null,
        "changed_files": null,
        "additions": null,
        "deletions": null,
        "comments": null,
        "review_comments": null,
        "labels": [],
        "url": "https://github.com/banksystembg/BankSystem/pull/226"
    },
    {
        "id": 584099874,
        "number": 225,
        "title": "Migrate to 3.1 & refactor",
        "state": "closed",
        "draft": false,
        "merged": true,
        "created_at": "2021-03-03T16:37:57Z",
        "updated_at": "2021-03-03T17:07:02Z",
        "closed_at": "2021-03-03T17:07:01Z",
        "merged_at": "2021-03-03T17:07:01Z",
        "author": "melikpehlivanov",
        "base_branch": "master",
        "head_branch": "migrate-3.1",
        "commits": null,
        "changed_files": null,
        "additions": null,
        "deletions": null,
        "comments": null,
        "review_comments": null,
        "labels": [
            "enhancement"
        ],
        "url": "https://github.com/banksystembg/BankSystem/pull/225"
    },
    {
        "id": 444393645,
        "number": 224,
        "title": "Add AsNoTracking in DemoShop to optimize ef performance",
        "state": "closed",
        "draft": false,
        "merged": true,
        "created_at": "2020-07-05T11:19:37Z",
        "updated_at": "2020-07-05T11:26:07Z",
        "closed_at": "2020-07-05T11:26:06Z",
        "merged_at": "2020-07-05T11:26:06Z",
        "author": "melikpehlivanov",
        "base_branch": "master",
        "head_branch": "optimize-ef-performance-in-demoshop",
        "commits": null,
        "changed_files": null,
        "additions": null,
        "deletions": null,
        "comments": null,
        "review_comments": null,
        "labels": [
            "enhancement"
        ],
        "url": "https://github.com/banksystembg/BankSystem/pull/224"
    },
    {
        "id": 444305742,
        "number": 223,
        "title": "Add new project links in README.md",
        "state": "closed",
        "draft": false,
        "merged": true,
        "created_at": "2020-07-04T16:50:34Z",
        "updated_at": "2020-07-05T11:08:39Z",
        "closed_at": "2020-07-05T11:08:38Z",
        "merged_at": "2020-07-05T11:08:37Z",
        "author": "martinmladenov",
        "base_branch": "master",
        "head_branch": "readme-links",
        "commits": null,
        "changed_files": null,
        "additions": null,
        "deletions": null,
        "comments": null,
        "review_comments": null,
        "labels": [
            "enhancement"
        ],
        "url": "https://github.com/banksystembg/BankSystem/pull/223"
    },
    {
        "id": 444256847,
        "number": 222,
        "title": "Implement Rsa key generator",
        "state": "closed",
        "draft": false,
        "merged": true,
        "created_at": "2020-07-04T08:27:36Z",
        "updated_at": "2020-07-05T08:10:42Z",
        "closed_at": "2020-07-05T08:10:41Z",
        "merged_at": "2020-07-05T08:10:41Z",
        "author": "melikpehlivanov",
        "base_branch": "master",
        "head_branch": "add-rsa-key-generator",
        "commits": null,
        "changed_files": null,
        "additions": null,
        "deletions": null,
        "comments": null,
        "review_comments": null,
        "labels": [
            "enhancement"
        ],
        "url": "https://github.com/banksystembg/BankSystem/pull/222"
    },
    {
        "id": 415095351,
        "number": 221,
        "title": "Add AsNoTracking where needed in services",
        "state": "closed",
        "draft": false,
        "merged": true,
        "created_at": "2020-05-08T07:38:23Z",
        "updated_at": "2020-05-08T08:01:31Z",
        "closed_at": "2020-05-08T08:01:28Z",
        "merged_at": "2020-05-08T08:01:28Z",
        "author": "melikpehlivanov",
        "base_branch": "master",
        "head_branch": "optimize-ef-performance",
        "commits": null,
        "changed_files": null,
        "additions": null,
        "deletions": null,
        "comments": null,
        "review_comments": null,
        "labels": [
            "enhancement"
        ],
        "url": "https://github.com/banksystembg/BankSystem/pull/221"
    },
    {
        "id": 299549433,
        "number": 219,
        "title": "Optimize pagination",
        "state": "closed",
        "draft": false,
        "merged": true,
        "created_at": "2019-07-20T09:01:15Z",
        "updated_at": "2019-07-20T13:13:43Z",
        "closed_at": "2019-07-20T13:13:40Z",
        "merged_at": "2019-07-20T13:13:40Z",
        "author": "melikpehlivanov",
        "base_branch": "master",
        "head_branch": "optimize-pagination",
        "commits": null,
        "changed_files": null,
        "additions": null,
        "deletions": null,
        "comments": null,
        "review_comments": null,
        "labels": [
            "enhancement"
        ],
        "url": "https://github.com/banksystembg/BankSystem/pull/219"
    },
    {
        "id": 272827125,
        "number": 217,
        "title": "Update README.md",
        "state": "closed",
        "draft": false,
        "merged": true,
        "created_at": "2019-04-23T17:38:09Z",
        "updated_at": "2019-04-23T17:40:49Z",
        "closed_at": "2019-04-23T17:40:47Z",
        "merged_at": "2019-04-23T17:40:47Z",
        "author": "melikpehlivanov",
        "base_branch": "master",
        "head_branch": "update-readme",
        "commits": null,
        "changed_files": null,
        "additions": null,
        "deletions": null,
        "comments": null,
        "review_comments": null,
        "labels": [],
        "url": "https://github.com/banksystembg/BankSystem/pull/217"
    },
    {
        "id": 270312884,
        "number": 216,
        "title": "Extract config error messages in constant",
        "state": "closed",
        "draft": false,
        "merged": false,
        "created_at": "2019-04-14T17:26:44Z",
        "updated_at": "2019-04-14T17:31:46Z",
        "closed_at": "2019-04-14T17:30:54Z",
        "merged_at": null,
        "author": "melikpehlivanov",
        "base_branch": "master",
        "head_branch": "move-error-messages-in-constants-in-startup",
        "commits": null,
        "changed_files": null,
        "additions": null,
        "deletions": null,
        "comments": null,
        "review_comments": null,
        "labels": [
            "enhancement"
        ],
        "url": "https://github.com/banksystembg/BankSystem/pull/216"
    },
    {
        "id": 270312725,
        "number": 214,
        "title": "Fix password validation regex",
        "state": "closed",
        "draft": false,
        "merged": true,
        "created_at": "2019-04-14T17:24:13Z",
        "updated_at": "2019-04-14T17:24:58Z",
        "closed_at": "2019-04-14T17:24:54Z",
        "merged_at": "2019-04-14T17:24:54Z",
        "author": "martinmladenov",
        "base_branch": "master",
        "head_branch": "fix-213",
        "commits": null,
        "changed_files": null,
        "additions": null,
        "deletions": null,
        "comments": null,
        "review_comments": null,
        "labels": [
            "bug",
            "High priority"
        ],
        "url": "https://github.com/banksystembg/BankSystem/pull/214"
    },
    {
        "id": 270307658,
        "number": 212,
        "title": "Fix 2FA key null after entering an invalid password",
        "state": "closed",
        "draft": false,
        "merged": true,
        "created_at": "2019-04-14T16:05:21Z",
        "updated_at": "2019-04-14T16:08:37Z",
        "closed_at": "2019-04-14T16:08:35Z",
        "merged_at": "2019-04-14T16:08:34Z",
        "author": "martinmladenov",
        "base_branch": "master",
        "head_branch": "fix-211",
        "commits": null,
        "changed_files": null,
        "additions": null,
        "deletions": null,
        "comments": null,
        "review_comments": null,
        "labels": [
            "bug"
        ],
        "url": "https://github.com/banksystembg/BankSystem/pull/212"
    },
    {
        "id": 270299118,
        "number": 210,
        "title": "Remove unused ShortName column in CentralApi database",
        "state": "closed",
        "draft": false,
        "merged": true,
        "created_at": "2019-04-14T14:00:04Z",
        "updated_at": "2019-04-14T14:12:17Z",
        "closed_at": "2019-04-14T14:12:14Z",
        "merged_at": "2019-04-14T14:12:14Z",
        "author": "martinmladenov",
        "base_branch": "master",
        "head_branch": "remove-shortname",
        "commits": null,
        "changed_files": null,
        "additions": null,
        "deletions": null,
        "comments": null,
        "review_comments": null,
        "labels": [
            "enhancement"
        ],
        "url": "https://github.com/banksystembg/BankSystem/pull/210"
    },
    {
        "id": 270084396,
        "number": 208,
        "title": "Update README.md",
        "state": "closed",
        "draft": false,
        "merged": true,
        "created_at": "2019-04-12T16:56:37Z",
        "updated_at": "2019-04-12T17:53:03Z",
        "closed_at": "2019-04-12T17:53:00Z",
        "merged_at": "2019-04-12T17:53:00Z",
        "author": "melikpehlivanov",
        "base_branch": "master",
        "head_branch": "update-readme",
        "commits": null,
        "changed_files": null,
        "additions": null,
        "deletions": null,
        "comments": null,
        "review_comments": null,
        "labels": [
            "enhancement"
        ],
        "url": "https://github.com/banksystembg/BankSystem/pull/208"
    },
    {
        "id": 270031353,
        "number": 207,
        "title": "Add unit tests for BankAccountUniqueHelper",
        "state": "closed",
        "draft": false,
        "merged": true,
        "created_at": "2019-04-12T14:20:24Z",
        "updated_at": "2019-04-12T15:19:38Z",
        "closed_at": "2019-04-12T15:19:34Z",
        "merged_at": "2019-04-12T15:19:34Z",
        "author": "melikpehlivanov",
        "base_branch": "master",
        "head_branch": "add-unit-tets-for-bank-helper",
        "commits": null,
        "changed_files": null,
        "additions": null,
        "deletions": null,
        "comments": null,
        "review_comments": null,
        "labels": [
            "enhancement"
        ],
        "url": "https://github.com/banksystembg/BankSystem/pull/207"
    }
]